prop/__init__.py
prop/__main__.py
prop/config.json
tests/__init__.py
tests/test_parse.py
tests/test_recursive.py
tests/test_request.py
prop_request-1.2.7.dist-info/LICENSE
prop_request-1.2.7.dist-info/METADATA
prop_request-1.2.7.dist-info/WHEEL
prop_request-1.2.7.dist-info/entry_points.txt
prop_request-1.2.7.dist-info/top_level.txt
prop_request-1.2.7.dist-info/RECORD
