Metadata-Version: 2.1
Name: prop-request
Version: 1.2.7
Summary: HTTP request tool with a little functionality
Home-page: https://github.com/mino-38/prop
Author: minomushi
License: MIT
Keywords: crawler parser html
Classifier: Programming Language :: Python :: 3.7
Classifier: Programming Language :: Python :: 3.8
Classifier: Programming Language :: Python :: 3.9
License-File: LICENSE
Requires-Dist: requests[socks]
Requires-Dist: beautifulsoup4
Requires-Dist: fake-useragent
Requires-Dist: robotsparsetools
Requires-Dist: tqdm
Requires-Dist: packaging
